[
    {
        "score": 95.59407043457031,
        "document": "AMZN_0001018724-22-000004",
        "file": "passage_152.txt",
        "text": "results had the foreign exchange rates remained the same as those in effect in the comparable prior year period. The effect on our net sales, operating expenses, and operating income from changes in our foreign exchange rates versus the U.S. Dollar is as follows (in millions): Year Ended December 31, 2021 Year Ended December 31, 2022 Exchange At Prior Exchange At Prior As Rate Year As Rate Year Reported Effect (1) Rates (2) Reported Effect (1) Rates (2) Net sales $ 469,822 $ (3,804) $466,018 $ 513,983 $ 15,495 $ 529,478 Operating expenses 444,943 (3,653) 441,290 501,735 16,356 518,091 Operating income 24,879 (151) 24,728 12,248 (861) 11,387 ___________________ (1) Represents the change in reported amounts resulting from changes in foreign"
    },
    {
        "score": 101.50146484375,
        "document": "AMZN_0001018724-22-000004",
        "file": "passage_285.txt",
        "text": "Effective January 1, 2022, research and development expenses are required to be capitalized and amortized for U.S. tax purposes. The components of the provision (benefit) for income taxes, net are as follows (in millions): Year Ended December 31, 2020 2021 2022 U.S. Federal: Current $ 1,835 $ 2,129 $ 2,175 Deferred (151) 155 (6,686) Total 1,684 2,284 (4,511) U.S. State: Current 626 763 1,074 Deferred (190) (178) (1,302) Total 436 585 (228) International: Current 956 2,209 1,682 Deferred (213) (287) (160) Total 743 1,922 1,522 Provision (benefit) for income taxes, net $ 2,863 $ 4,791 $ (3,217) U.S. and international components of income (loss) before income taxes are as follows (in millions): Year Ended December 31, 2020 2021 2022 U.S."
    },
    {
        "score": 101.94949340820312,
        "document": "AMZN_0001018724-22-000004",
        "file": "passage_308.txt",
        "text": "and $20 million in 2020, 2021, and 2022. U.S. property and equipment, net and operating leases were $109.5 billion, $155.0 billion, and $180.0 billion, as of December 31, 2020, 2021, and 2022, and non-U.S. property and equipment, net and operating leases were $41.2 billion, $61.3 billion, and $72.9 billion as of December 31, 2020, 2021, and 2022. Except for the U.S., property and equipment, net and operating leases in any single country were less than 10% of consolidated property and equipment, net and operating leases. Depreciation and amortization expense on property and equipment, including corporate property and equipment, are allocated to all segments based on usage. Total depreciation and amortization expense, by segment, is as follows (in millions): Year Ended"
    },
    {
        "score": 102.524169921875,
        "document": "AMZN_0001018724-22-000004",
        "file": "passage_242.txt",
        "text": "7 Total cash, cash equivalents, and restricted cash shown in the consolidated statements of cash flows $ 36,477 $ 54,253 Note 3 \u2014 PROPERTY AND EQUIPMENT Property and equipment, at cost, consisted of the following (in millions): December 31, 2021 2022 Gross property and equipment (1): Land and buildings $ 81,104 $ 91,650 Equipment 128,683 157,458 Other assets 4,118 4,602 Construction in progress 24,895 30,020 Gross property and equipment 238,800 283,730 Total accumulated depreciation and amortization (1) 78,519 97,015 Total property and equipment, net $ 160,281 $ 186,715 __________________ (1) Includes the original cost and accumulated depreciation of fully-depreciated assets. Depreciation and amortization expense on property and equipment was $16.2 billion, $22.9 billion, and $24.9 billion which includes amortization of"
    },
    {
        "score": 102.81123352050781,
        "document": "AMZN_0001018724-22-000004",
        "file": "passage_261.txt",
        "text": "1,027 982 622 8,652 16,064 Total commitments $ 32,360 $ 32,856 $ 25,626 $ 22,056 $24,826 $150,865 $288,589 ___________________ (1) Includes non-cancellable financing obligations for fulfillment, sortation, and data center facilities. Excluding interest, current financing obligations of $196 million and $266 million are recorded within \u201cAccrued expenses and other\u201d and $6.2 billion and $6.7 billion are recorded within \u201cOther long-term liabilities\u201d as of December 31, 2021 and 2022. The weighted-average remaining term of the financing obligations was 18.8 years and 17.9 years and the weighted-average imputed interest rate was 3.2% and 3.1% as of December 31, 2021 and 2022. (2) Includes unconditional purchase obligations related to long-term agreements to acquire and license digital media content that are not reflected on"
    }
]